<?xml version="1.0" encoding="UTF-8"?><nfeProc versao="2.00" xmlns="http://www.portalfiscal.inf.br/nfe"><NFe xmlns="http://www.portalfiscal.inf.br/nfe"><infNFe versao="2.00" Id="NFe22130523314594004874550020000204851861474324"><ide><cUF>22</cUF><cNF>86147432</cNF><natOp>TRANSFERENCIA MERC. ADQ./REC</natOp><indPag>2</indPag><mod>55</mod><serie>2</serie><nNF>20485</nNF><dEmi>2013-05-10</dEmi><dSaiEnt>2013-05-10</dSaiEnt><hSaiEnt>20:41:00</hSaiEnt><tpNF>1</tpNF><cMunFG>2211001</cMunFG><tpImp>1</tpImp><tpEmis>1</tpEmis><cDV>4</cDV><tpAmb>1</tpAmb><finNFe>1</finNFe><procEmi>0</procEmi><verProc>2.02</verProc></ide><emit><CNPJ>23314594004874</CNPJ><xNome>ALESAT COMBUSTIVEIS S.A</xNome><enderEmit><xLgr>AV DEPUTADO PAULO FERRAZ</xLgr><nro>S/N</nro><xCpl>PATIO FERROV. DO ITARARE</xCpl><xBairro>LIVRAMENTO</xBairro><cMun>2211001</cMun><xMun>TERESINA</xMun><UF>PI</UF><CEP>64078820</CEP><cPais>1058</cPais><xPais>BRASIL</xPais><fone>8632356946</fone></enderEmit><IE>194818551</IE><IEST>123549574</IEST><IM>105431-7</IM><CNAE>4681801</CNAE><CRT>3</CRT></emit><dest><CNPJ>23314594003630</CNPJ><xNome>ALESAT COMBUSTIVEIS S.A</xNome><enderDest><xLgr>AVENIDA DOS PORTUGUESES</xLgr><nro>025</nro><xCpl>A SALA 01 A</xCpl><xBairro>VILA EMBRATEL</xBairro><cMun>2111300</cMun><xMun>SAO LUIS</xMun><UF>MA</UF><CEP>65085581</CEP><cPais>1058</cPais><xPais>BRASIL</xPais><fone>0000000</fone></enderDest><IE>122313550</IE></dest><retirada><CNPJ>34274233032306</CNPJ><xLgr>AVENIDA DEP. PAULO FERRAZ</xLgr><nro>S/N</nro><xBairro>DIRCEU ARCOVERDE</xBairro><cMun>2211001</cMun><xMun>TERESINA</xMun><UF>PI</UF></retirada><det nItem="1"><prod><cProd>AEHC</cProd><cEAN/><xProd>ETANOL E. HIDRATADO NO ONU 1170 CL 3 GRP</xProd><NCM>22071010</NCM><CFOP>6659</CFOP><uCom>LTS</uCom><qCom>24883.0000</qCom><vUnCom>1.4455000000</vUnCom><vProd>35968.38</vProd><cEANTrib/><uTrib>LTS</uTrib><qTrib>24883.0000</qTrib><vUnTrib>1.4455000000</vUnTrib><indTot>1</indTot><comb><cProdANP>810101001</cProdANP><UFCons>MA</UFCons></comb></prod><imposto><ICMS><ICMS00><orig>0</orig><CST>00</CST><modBC>3</modBC><vBC>35968.38</vBC><pICMS>12.00</pICMS><vICMS>4316.21</vICMS></ICMS00></ICMS><PIS><PISNT><CST>07</CST></PISNT></PIS><COFINS><COFINSNT><CST>07</CST></COFINSNT></COFINS></imposto></det><total><ICMSTot><vBC>35968.38</vBC><vICMS>4316.21</vICMS><vBCST>0.00</vBCST><vST>0.00</vST><vProd>35968.38</vProd><vFrete>0.00</vFrete><vSeg>0.00</vSeg><vDesc>0.00</vDesc><vII>0.00</vII><vIPI>0.00</vIPI><vPIS>0.00</vPIS><vCOFINS>0.00</vCOFINS><vOutro>0.00</vOutro><vNF>35968.38</vNF></ICMSTot></total><transp><modFrete>1</modFrete><transporta><CNPJ>13080196000113</CNPJ><xNome>DAFONTE TRANSPORTES LTDA</xNome><IE>042996392</IE><xEnder>AVENIDA AV. SANTA LUCIA 123</xEnder><xMun>JABOATAO DOS GUARARA</xMun><UF>PE</UF></transporta><veicTransp><placa>PFI5604</placa><UF>PE</UF></veicTransp><reboque><placa>PFX3658</placa><UF>PE</UF></reboque><vol><qVol>24883</qVol><esp>LTS</esp><marca>S/M</marca><pesoL>19981.050</pesoL><pesoB>19981.050</pesoB></vol></transp><infAdic><infCpl>DADOS CARREGAMENTO CONFORME LAUDO EMANEXO, LACRES 303820/303886/4531279 FAT: 0.9953 PH 7.3 ACIDEZ TEMP ENS. 25.5DENS 0.818 INFORMACAO AO DESTINATARIO:DECLARAMOS QUE O(S) PRODUTO(S) ESTA(AO) ADEQUADAMENTE ACONDICIONADO(S) PARA SUPORTAR OS RISCOS NORMAIS DE CARREGAMENTO, DESCARREGAMENTOTRANSPORTE E TRANSBORDO, CONFORME A REGULAMENTACAO EM VIGOR.</infCpl></infAdic></infNFe><Signature xmlns="http://www.w3.org/2000/09/xmldsig#"><SignedInfo><CanonicalizationMethod Algorithm="http://www.w3.org/TR/2001/REC-xml-c14n-20010315"/><SignatureMethod Algorithm="http://www.w3.org/2000/09/xmldsig#rsa-sha1"/><Reference URI="#NFe22130523314594004874550020000204851861474324"><Transforms><Transform Algorithm="http://www.w3.org/2000/09/xmldsig#enveloped-signature"/><Transform Algorithm="http://www.w3.org/TR/2001/REC-xml-c14n-20010315"/></Transforms><DigestMethod Algorithm="http://www.w3.org/2000/09/xmldsig#sha1"/><DigestValue>B//EkpZbhmShva041G6Mlr+VMFs=</DigestValue></Reference></SignedInfo><SignatureValue>B//EkpZbhmShva041G6Mlr+VMFs=</SignatureValue><KeyInfo><X509Data><X509Certificate>B//EkpZbhmShva041G6Mlr+VMFs=</X509Certificate></X509Data></KeyInfo></Signature></NFe><protNFe versao="2.00"><infProt><tpAmb>1</tpAmb><verAplic>2.02</verAplic><chNFe>22130523314594004874550020000204851861474324</chNFe><dhRecbto>2013-05-10T20:42:35</dhRecbto><nProt>422130005147385</nProt><digVal>B//EkpZbhmShva041G6Mlr+VMFs=</digVal><cStat>100</cStat><xMotivo>Autorizado o uso da NF-e</xMotivo></infProt></protNFe></nfeProc>
