<?xml version="1.0" encoding="UTF-8"?><nfeProc versao="2.00" xmlns="http://www.portalfiscal.inf.br/nfe"><NFe xmlns="http://www.portalfiscal.inf.br/nfe"><infNFe versao="2.00" Id="NFe31130323314594003045550020003427941272449060"><ide><cUF>31</cUF><cNF>27244906</cNF><natOp>TRANSFERENCIA MERC. ADQ./REC</natOp><indPag>2</indPag><mod>55</mod><serie>2</serie><nNF>342794</nNF><dEmi>2013-03-15</dEmi><dSaiEnt>2013-03-15</dSaiEnt><hSaiEnt>15:10:00</hSaiEnt><tpNF>1</tpNF><cMunFG>3106705</cMunFG><tpImp>1</tpImp><tpEmis>1</tpEmis><cDV>0</cDV><tpAmb>1</tpAmb><finNFe>1</finNFe><procEmi>0</procEmi><verProc>2.02</verProc></ide><emit><CNPJ>23314594003045</CNPJ><xNome>ALESAT COMBUSTIVEIS S.A.</xNome><enderEmit><xLgr>RODOVIA FERNAO DIAS</xLgr><nro>S/N</nro><xCpl>KM427</xCpl><xBairro>BARREIRO DE CIMA</xBairro><cMun>3106705</cMun><xMun>BETIM</xMun><UF>MG</UF><CEP>32500000</CEP><cPais>1058</cPais><xPais>BRASIL</xPais><fone>3130739200</fone></enderEmit><IE>0676156930255</IE><IM>5573/001-9</IM><CNAE>4681801</CNAE><CRT>3</CRT></emit><dest><CNPJ>23314594003711</CNPJ><xNome>ALESAT COMBUSTIVEIS S.A</xNome><enderDest><xLgr>AVENIDA AV. LINCOLN ALVES DOS SANTOS</xLgr><nro>056</nro><xCpl>SL 3</xCpl><xBairro>DISTRITO INDUSTRIAL</xBairro><cMun>3143302</cMun><xMun>MONTES CLAROS</xMun><UF>MG</UF><CEP>39404005</CEP><cPais>1058</cPais><xPais>BRASIL</xPais><fone>0000000</fone></enderDest><IE>0676156931995</IE></dest><det nItem="1"><prod><cProd>GAA</cProd><cEAN/><xProd>GASOLINA TIPO &quot;A&quot; ONU 1203 CL 3 GRP. EMB</xProd><NCM>27101259</NCM><CFOP>5659</CFOP><uCom>LTS</uCom><qCom>44568.0000</qCom><vUnCom>2.4750000000</vUnCom><vProd>110305.80</vProd><cEANTrib/><uTrib>LTS</uTrib><qTrib>44568.0000</qTrib><vUnTrib>2.4750000000</vUnTrib><indTot>1</indTot><comb><cProdANP>320101001</cProdANP><UFCons>MG</UFCons></comb></prod><imposto><ICMS><ICMS60><orig>0</orig><CST>60</CST></ICMS60></ICMS><PIS><PISNT><CST>04</CST></PISNT></PIS><COFINS><COFINSNT><CST>04</CST></COFINSNT></COFINS></imposto></det><total><ICMSTot><vBC>0.00</vBC><vICMS>0.00</vICMS><vBCST>0.00</vBCST><vST>0.00</vST><vProd>110305.80</vProd><vFrete>0.00</vFrete><vSeg>0.00</vSeg><vDesc>0.00</vDesc><vII>0.00</vII><vIPI>0.00</vIPI><vPIS>0.00</vPIS><vCOFINS>0.00</vCOFINS><vOutro>0.00</vOutro><vNF>110305.80</vNF></ICMSTot></total><transp><modFrete>1</modFrete><transporta><CNPJ>02331952000113</CNPJ><xNome>COOP. TRAB. AUT. TRANSP. CARGAS LTDA</xNome><IE>0677319040092</IE><xEnder>RUA R ARATICUM</xEnder><xMun>BETIM</xMun><UF>MG</UF></transporta><veicTransp><placa>GXA5913</placa><UF>MG</UF></veicTransp><reboque><placa>HBG7796</placa><UF>MG</UF></reboque><vol><qVol>44568</qVol><esp>LTS</esp><marca>S/M</marca><pesoL>32044.390</pesoL><pesoB>32044.390</pesoB></vol></transp><infAdic><infCpl>ICMS RETIDO POR SUBST. TRIBUTARIA NOS TERMOS DO ART. 73, INCISO II DO ANEXO XV DO RICMS/MGTemp do CT 28,5.C Densidade 20,0.C 0,726 OR 609268 INFORMACAO AO DESTINATARIO: (GAA)Destino BCR: 165717.19 ICMR: 44743.64 Origem BCR: 165717.19 ICMR: 44743.64 Lacres Cor / Remessa / Quantidade: AZ / 09401 / 6 Lacres Nrs.: 0008632285, 0008632286, 0008632287, 0008632288, 0008632289, 0008632290, Lacres Nrs.: DECLARAMOS QUE O(S) PRODUTO(S) ESTA(AO) ADEQUADAMENTE ACONDICIONADO(S) PARA SUPORTAR OS RISCOS NORMAIS DE CARREGAMENTO, DESCARREGAMENTOTRANSPORTE E TRANSBORDO, CONFORME A REGULAMENTACAO EM VIGOR.BOLETIM(NS) CONFORMIDADE : 2009/00203,</infCpl></infAdic></infNFe><Signature xmlns="http://www.w3.org/2000/09/xmldsig#"><SignedInfo><CanonicalizationMethod Algorithm="http://www.w3.org/TR/2001/REC-xml-c14n-20010315"/><SignatureMethod Algorithm="http://www.w3.org/2000/09/xmldsig#rsa-sha1"/><Reference URI="#NFe31130323314594003045550020003427941272449060"><Transforms><Transform Algorithm="http://www.w3.org/2000/09/xmldsig#enveloped-signature"/><Transform Algorithm="http://www.w3.org/TR/2001/REC-xml-c14n-20010315"/></Transforms><DigestMethod Algorithm="http://www.w3.org/2000/09/xmldsig#sha1"/><DigestValue>twHLPs0P0I5SVGfTh+eWkTwKKHA=</DigestValue></Reference></SignedInfo><SignatureValue>twHLPs0P0I5SVGfTh+eWkTwKKHA=</SignatureValue><KeyInfo><X509Data><X509Certificate>twHLPs0P0I5SVGfTh+eWkTwKKHA=</X509Certificate></X509Data></KeyInfo></Signature></NFe><protNFe versao="2.00"><infProt><tpAmb>1</tpAmb><verAplic>2.02</verAplic><chNFe>31130323314594003045550020003427941272449060</chNFe><dhRecbto>2013-03-15T15:09:36</dhRecbto><nProt>131131032559207</nProt><digVal>twHLPs0P0I5SVGfTh+eWkTwKKHA=</digVal><cStat>100</cStat><xMotivo>Autorizado o uso da NF-e</xMotivo></infProt></protNFe></nfeProc>
