<?xml version="1.0" encoding="UTF-8"?><nfeProc versao="2.00" xmlns="http://www.portalfiscal.inf.br/nfe"><NFe xmlns="http://www.portalfiscal.inf.br/nfe"><infNFe versao="2.00" Id="NFe21130123314594003630550020000973641946183870"><ide><cUF>21</cUF><cNF>94618387</cNF><natOp>TRANSFERENCIA MERC. ADQ./REC</natOp><indPag>2</indPag><mod>55</mod><serie>2</serie><nNF>97364</nNF><dEmi>2013-01-02</dEmi><dSaiEnt>2013-01-02</dSaiEnt><hSaiEnt>07:55:00</hSaiEnt><tpNF>1</tpNF><cMunFG>2111300</cMunFG><tpImp>1</tpImp><tpEmis>1</tpEmis><cDV>0</cDV><tpAmb>1</tpAmb><finNFe>1</finNFe><procEmi>0</procEmi><verProc>2.02</verProc></ide><emit><CNPJ>23314594003630</CNPJ><xNome>ALESAT COMBUSTIVEIS S.A</xNome><enderEmit><xLgr>AVENIDA DOS PORTUQUESES</xLgr><nro>025</nro><xCpl>A</xCpl><xBairro>VILA EMBRATEL</xBairro><cMun>2111300</cMun><xMun>SAO LUIS</xMun><UF>MA</UF><CEP>65085580</CEP><cPais>1058</cPais><xPais>BRASIL</xPais><fone>9821077956</fone></enderEmit><IE>122313550</IE><IEST>194613690</IEST><IM>5861800-4</IM><CNAE>4681801</CNAE><CRT>3</CRT></emit><dest><CNPJ>23314594004874</CNPJ><xNome>ALESAT COMBUSTIVEIS S.A.</xNome><enderDest><xLgr>AVENIDA DEPUTADO PAULO FERRAZ</xLgr><nro>S/N</nro><xBairro>LIVRAMENTO</xBairro><cMun>2211001</cMun><xMun>TERESINA</xMun><UF>PI</UF><CEP>64078820</CEP><cPais>1058</cPais><xPais>BRASIL</xPais><fone>8632356946</fone></enderDest><IE>194818551</IE></dest><retirada><CNPJ>44983435000330</CNPJ><xLgr>PORTO DO ITAQUI</xLgr><nro>S/N</nro><xBairro>PORTO DO ITAQUI</xBairro><cMun>2111300</cMun><xMun>SAO LUIS</xMun><UF>MA</UF></retirada><det nItem="1"><prod><cProd>GAA</cProd><cEAN/><xProd>GASOLINA TIPO &quot;A&quot; ONU 1203 CL 3 GRP. EMB</xProd><NCM>27101259</NCM><CFOP>6659</CFOP><uCom>LTS</uCom><qCom>59364.0000</qCom><vUnCom>2.4254000000</vUnCom><vProd>143981.45</vProd><cEANTrib/><uTrib>LTS</uTrib><qTrib>59364.0000</qTrib><vUnTrib>2.4254000000</vUnTrib><indTot>1</indTot><comb><cProdANP>320101001</cProdANP><UFCons>PI</UFCons></comb></prod><imposto><ICMS><ICMS60><orig>0</orig><CST>60</CST></ICMS60></ICMS><PIS><PISNT><CST>04</CST></PISNT></PIS><COFINS><COFINSNT><CST>04</CST></COFINSNT></COFINS></imposto></det><total><ICMSTot><vBC>0.00</vBC><vICMS>0.00</vICMS><vBCST>0.00</vBCST><vST>0.00</vST><vProd>143981.45</vProd><vFrete>0.00</vFrete><vSeg>0.00</vSeg><vDesc>0.00</vDesc><vII>0.00</vII><vIPI>0.00</vIPI><vPIS>0.00</vPIS><vCOFINS>0.00</vCOFINS><vOutro>0.00</vOutro><vNF>143981.45</vNF></ICMSTot></total><transp><modFrete>1</modFrete><transporta><CNPJ>09146222000191</CNPJ><xNome>TRANSPORTES IMPERADOR LTDA</xNome><IE>294032894</IE><xEnder>RODOVIA BR-226</xEnder><xMun>WANDERLANDIA</xMun><UF>TO</UF></transporta><veicTransp><placa>MWJ3380</placa><UF>TO</UF><RNTC>02585051</RNTC></veicTransp><reboque><placa>MVQ1369</placa><UF>TO</UF></reboque><vol><qVol>59364</qVol><esp>LTS</esp><marca>S/M</marca><pesoL>42682.720</pesoL><pesoB>42682.720</pesoB></vol></transp><infAdic><infCpl>ICMS RETIDO A SER PAGO NOS TERMOS DA CLAUSULA DECIMA PRIMEIRA DO CONVENIO ICMS No. 03/99 - PETROLEO BRASILEIRO S/ADENS A 20. 0,71820 / TEMP. 29 / FATOR0,98940 INFORMACAO AO DESTINATARIO: (GAA)Destino BCR: 197088.48 ICMR: 49272.12 Origem BCR: 207922.41 ICMR: 56139.05 Lacres Cor / Remessa / Quantidade: AM / 08725 / 12 Lacres Nrs.: 0008043565, 0008043566, 0008043567, 0008043568, 0008043569, 0008043570, Lacres Nrs.: 0008043571, 0008043572, 0008043573, 0008043574, 0008043575, 0008043576, DECLARAMOS QUE O(S) PRODUTO(S) ESTA(AO) ADEQUADAMENTE ACONDICIONADO(S) PARA SUPORTAR OS RISCOS NORMAIS DE CARREGAMENTO, DESCARREGAMENTOTRANSPORTE E TRANSBORDO, CONFORME A REGULAMENTACAO EM VIGOR.</infCpl></infAdic></infNFe><Signature xmlns="http://www.w3.org/2000/09/xmldsig#"><SignedInfo><CanonicalizationMethod Algorithm="http://www.w3.org/TR/2001/REC-xml-c14n-20010315"/><SignatureMethod Algorithm="http://www.w3.org/2000/09/xmldsig#rsa-sha1"/><Reference URI="#NFe21130123314594003630550020000973641946183870"><Transforms><Transform Algorithm="http://www.w3.org/2000/09/xmldsig#enveloped-signature"/><Transform Algorithm="http://www.w3.org/TR/2001/REC-xml-c14n-20010315"/></Transforms><DigestMethod Algorithm="http://www.w3.org/2000/09/xmldsig#sha1"/><DigestValue>sbQIfnjVCKXE8OuXhk4RLjCB5TM=</DigestValue></Reference></SignedInfo><SignatureValue>sbQIfnjVCKXE8OuXhk4RLjCB5TM=</SignatureValue><KeyInfo><X509Data><X509Certificate>sbQIfnjVCKXE8OuXhk4RLjCB5TM=</X509Certificate></X509Data></KeyInfo></Signature></NFe><protNFe versao="2.00"><infProt><tpAmb>1</tpAmb><verAplic>2.02</verAplic><chNFe>21130123314594003630550020000973641946183870</chNFe><dhRecbto>2013-01-02T07:53:44</dhRecbto><nProt>421130000003187</nProt><digVal>sbQIfnjVCKXE8OuXhk4RLjCB5TM=</digVal><cStat>100</cStat><xMotivo>Autorizado o uso da NF-e</xMotivo></infProt></protNFe></nfeProc>
